streamsculptor/_init_.py
streamsculptor-0.0.0.dist-info/METADATA
streamsculptor-0.0.0.dist-info/WHEEL
streamsculptor-0.0.0.dist-info/top_level.txt
streamsculptor-0.0.0.dist-info/RECORD
