Metadata-Version: 2.1
Name: streamsculptor
Version: 0.0.0
Summary: Stellar stream modeling package from Nibauer et al. 2024
Author-email: Jacob Nibauer <jnibauer@princeton.edu>
